LICENSE
MANIFEST.in
README.md
setup.py
django_vellum.egg-info/PKG-INFO
django_vellum.egg-info/SOURCES.txt
django_vellum.egg-info/dependency_links.txt
django_vellum.egg-info/not-zip-safe
django_vellum.egg-info/requires.txt
django_vellum.egg-info/top_level.txt
vellum/__init__.py
vellum/admin.py
vellum/context_processors.py
vellum/feeds.py
vellum/forms.py
vellum/managers.py
vellum/models.py
vellum/settings.py
vellum/sitemap.py
vellum/tests.py
vellum/urls.py
vellum/views.py
vellum/management/__init__.py
vellum/management/commands/__init__.py
vellum/management/commands/wordpress_import.py
vellum/templates/base.html
vellum/templates/admin/vellum/post/change_form.html
vellum/templates/feeds/post_description.html
vellum/templates/feeds/post_title.html
vellum/templates/inlines/default.html
vellum/templates/vellum/base_vellum.html
vellum/templates/vellum/category_detail.html
vellum/templates/vellum/category_list.html
vellum/templates/vellum/post_archive.html
vellum/templates/vellum/post_archive_day.html
vellum/templates/vellum/post_archive_month.html
vellum/templates/vellum/post_archive_year.html
vellum/templates/vellum/post_detail.html
vellum/templates/vellum/post_list.html
vellum/templates/vellum/post_search.html
vellum/templates/vellum/tag_detail.html
vellum/templates/vellum/tag_list.html
vellum/templates/vellum/includes/comments.html
vellum/templates/vellum/includes/disqus.html
vellum/templates/vellum/includes/menu.html
vellum/templates/vellum/includes/other_posts.html
vellum/templates/vellum/includes/pagination.html
vellum/templates/vellum/includes/post.html
vellum/templates/vellum/includes/post_content.html
vellum/templates/vellum/includes/post_meta.html
vellum/templates/vellum/includes/post_more.html
vellum/templates/vellum/includes/quick_search.html
vellum/templatetags/__init__.py
vellum/templatetags/vellum_archives.py
vellum/templatetags/vellum_tags.py