Metadata-Version: 1.1
Name: django-vellum
Version: 1.4.2
Summary: A web log for Django.
Home-page: https://github.com/pigmonkey/django-vellum
Author: Peter Hogg
Author-email: peter@havenaut.net
License: UNKNOWN
Platform: UNKNOWN
Classifier: Programming Language :: Python
Classifier: License :: OSI Approved :: BSD License
Classifier: Operating System :: OS Independent
Classifier: Development Status :: 5 - Production/Stable
Classifier: Framework :: Django
